{
  "id": "tutorial-basics/loan",
  "title": "loan",
  "description": "",
  "source": "@site/docs/tutorial-basics/loan.md",
  "sourceDirName": "tutorial-basics",
  "slug": "/tutorial-basics/loan",
  "permalink": "/docs/tutorial-basics/loan",
  "draft": false,
  "unlisted": false,
  "editUrl": "https://github.com/facebook/docusaurus/tree/main/packages/create-docusaurus/templates/shared/docs/tutorial-basics/loan.md",
  "tags": [],
  "version": "current",
  "frontMatter": {},
  "sidebar": "tutorialSidebar",
  "previous": {
    "title": "invites",
    "permalink": "/docs/tutorial-basics/invites"
  },
  "next": {
    "title": "Mobile",
    "permalink": "/docs/tutorial-basics/mobile"
  }
}