{
  "id": "api/User/Release User by Admin",
  "title": "Release User by Admin",
  "description": "The functions described is accessible only to users with ADMIN privileges.",
  "source": "@site/docs/api/User/Release User by Admin.md",
  "sourceDirName": "api/User",
  "slug": "/api/User/Release User by Admin",
  "permalink": "/docs/api/User/Release User by Admin",
  "draft": false,
  "unlisted": false,
  "editUrl": "https://github.com/facebook/docusaurus/tree/main/packages/create-docusaurus/templates/shared/docs/api/User/Release User by Admin.md",
  "tags": [],
  "version": "current",
  "frontMatter": {},
  "sidebar": "apiSidebar",
  "previous": {
    "title": "Make Allow Location",
    "permalink": "/docs/api/User/Make Allow Location"
  },
  "next": {
    "title": "Request Email Change",
    "permalink": "/docs/api/User/Request Email Change"
  }
}